sniimapp/__init__.py
sniimapp/sniimapp_precios.py
sniimapp-0.1.4.dist-info/METADATA
sniimapp-0.1.4.dist-info/WHEEL
sniimapp-0.1.4.dist-info/top_level.txt
sniimapp-0.1.4.dist-info/RECORD
