Metadata-Version: 2.1
Name: sniimapp
Version: 0.1.4
Summary: API - Observatorio de gestión pública e inteligencia de mercados
Home-page: https://sites.google.com/umich.mx/observatoriofcca
Author: Rodolfo Lopez
Author-email: 1803672F@umich.mx
License: UNKNOWN
Platform: UNKNOWN
Classifier: Programming Language :: Python :: 3
Classifier: License :: OSI Approved :: MIT License
Classifier: Operating System :: OS Independent
Requires-Dist: requests
